cloud_detect/__init__.py
cloud_detect/providers/__init__.py
cloud_detect/providers/alibaba_provider.py
cloud_detect/providers/aws_provider.py
cloud_detect/providers/azure_provider.py
cloud_detect/providers/do_provider.py
cloud_detect/providers/gcp_provider.py
cloud_detect/providers/oci_provider.py
cloud_detect/providers/provider.py
cloud_detect/providers/vultr_provider.py
cloud_detect-0.0.13.dist-info/LICENSE.md
cloud_detect-0.0.13.dist-info/METADATA
cloud_detect-0.0.13.dist-info/WHEEL
cloud_detect-0.0.13.dist-info/top_level.txt
cloud_detect-0.0.13.dist-info/RECORD
