Metadata-Version: 2.1
Name: cloud-detect
Version: 0.0.13
Summary: Module that determines a host's cloud provider
Home-page: https://github.com/dgzlopes/cloud-detect
Author: Daniel Gonzalez Lopes
Author-email: danielgonzalezlopes@gmail.com
License: MIT
Classifier: Development Status :: 3 - Alpha
Classifier: Intended Audience :: Developers
Classifier: Natural Language :: English
Classifier: Programming Language :: Python :: 3.6
Classifier: Programming Language :: Python :: 3.7
Classifier: Programming Language :: Python :: 3.8
Classifier: Programming Language :: Python :: 3.9
Classifier: Programming Language :: Python :: 3.10
Classifier: Programming Language :: Python :: 3.11
Classifier: License :: OSI Approved :: MIT License
Classifier: Operating System :: POSIX :: Linux
Classifier: Topic :: Software Development :: Libraries :: Python Modules
Classifier: Topic :: System :: Systems Administration
Classifier: Topic :: System :: Networking
Requires-Python: >=3.6
License-File: LICENSE.md
Requires-Dist: aiohttp >=3.7
